{
  "categories": [
    {
      "category": "Roswell Office",
      "vendors": [
        {
          "name": "Devin Wilson (Plaza POC)",
          "phone": "910-262-7583"
        },
        {
          "name": "Flying Locksmiths (Sue Allen)",
          "phone": "678-462-9024"
        }
      ]
    },
    {
      "category": "Rome Office",
      "vendors": [
        {
          "name": "Dr. Vargo (Building)",
          "phone": "706-290-0011"
        }
      ]
    },
    {
      "category": "Canton Office",
      "vendors": [
        {
          "name": "Controlled Climate Services (HVAC)",
          "phone": "770-432-3869"
        }
      ]
    },
    {
      "category": "Jasper Office",
      "vendors": [
        {
          "name": "Sonny Galloway (GCCI Buildings)",
          "phone": "770-296-0816"
        }
      ]
    },
    {
      "category": "Extinguisher & Alarm Inspections",
      "vendors": [
        {
          "name": "Alliance Fire \u2014 Inspections (Canton)",
          "phone": "678-680-5742"
        },
        {
          "name": "Alliance Fire \u2014 Alarm (Canton)",
          "phone": "770-554-5004"
        }
      ]
    }
  ]
}